idreamofgenie/__init__.py
idreamofgenie/basic.py
idreamofgenie/connect.py
idreamofgenie-0.1.1.data/scripts/find-host
idreamofgenie-0.1.1.dist-info/LICENSE
idreamofgenie-0.1.1.dist-info/METADATA
idreamofgenie-0.1.1.dist-info/WHEEL
idreamofgenie-0.1.1.dist-info/top_level.txt
idreamofgenie-0.1.1.dist-info/RECORD
